color_detect/__init__.py
color_detect/color_detection.py
color_detect-0.0.1.dist-info/METADATA
color_detect-0.0.1.dist-info/WHEEL
color_detect-0.0.1.dist-info/top_level.txt
color_detect-0.0.1.dist-info/RECORD
