Metadata-Version: 2.1
Name: color-detect
Version: 0.0.1
Summary: A mini package to work with detecting colors from images
Home-page: https://github.com/bashirk/color-detect
Author: Korede Bashir
Author-email: bashirkorede@gmail.com
License: MIT
Platform: UNKNOWN
Classifier: Programming Language :: Python :: 3
Classifier: License :: OSI Approved :: MIT License
Classifier: Operating System :: OS Independent
Requires-Dist: opencv-python
Requires-Dist: numpy
Requires-Dist: pandas
